README.rst
setup.cfg
setup.py
AndpayPyBase.egg-info/PKG-INFO
AndpayPyBase.egg-info/SOURCES.txt
AndpayPyBase.egg-info/dependency_links.txt
AndpayPyBase.egg-info/requires.txt
AndpayPyBase.egg-info/top_level.txt
pybase/__init__.py
pybase/dbutil.py