Metadata-Version: 1.1
Name: AndpayPyBase
Version: 1.0.1
Summary: andpay python base
Home-page: https://www.andpay.me
Author: jame.cen
Author-email: jame.cen@andpay.me
License: MIT
Keywords: andpay util base
Platform: UNKNOWN
Classifier: Development Status :: 3 - Alpha
Classifier: Intended Audience :: Developers
Classifier: Topic :: Software Development :: Build Tools
Classifier: License :: OSI Approved :: MIT License
Classifier: Programming Language :: Python :: 2
Classifier: Programming Language :: Python :: 2.6
Classifier: Programming Language :: Python :: 2.7
Classifier: Programming Language :: Python :: 3
Classifier: Programming Language :: Python :: 3.3
Classifier: Programming Language :: Python :: 3.4
Classifier: Programming Language :: Python :: 3.5
